README.rst
setup.py
surch/__init__.py
surch/constants.py
surch/organization.py
surch/repo.py
surch/surch.py
surch/utils.py
surch.egg-info/PKG-INFO
surch.egg-info/SOURCES.txt
surch.egg-info/dependency_links.txt
surch.egg-info/entry_points.txt
surch.egg-info/requires.txt
surch.egg-info/top_level.txt
surch/plugins/__init__.py
surch/plugins/handler.py
surch/plugins/pagerduty.py
surch/plugins/vault.py